vanilla_pkg/Dog.py
vanilla_pkg/Mocks.py
vanilla_pkg/__init__.py
vanilla_pkg-0.1.dist-info/METADATA
vanilla_pkg-0.1.dist-info/WHEEL
vanilla_pkg-0.1.dist-info/top_level.txt
vanilla_pkg-0.1.dist-info/RECORD
