Metadata-Version: 2.1
Name: vanilla_pkg
Version: 0.1
Summary: A small example package
Home-page: https://github.com/pypa/sampleproject
Author: Noah Spahn
Author-email: noah.spahn@ucsb.edu
License: UNKNOWN
Project-URL: Bug Tracker, https://github.com/Feralo/vanilla_pkg/issues
Platform: UNKNOWN
Classifier: Programming Language :: Python :: 3
Classifier: License :: OSI Approved :: MIT License
Classifier: Operating System :: OS Independent
Requires-Python: >=3.7
